LICENSE
README.md
sqlite3_backup/__init__.py
sqlite3_backup/_backup.py
sqlite3_backup-0.3.2.dist-info/LICENSE
sqlite3_backup-0.3.2.dist-info/WHEEL
sqlite3_backup-0.3.2.dist-info/METADATA
sqlite3_backup-0.3.2.dist-info/RECORD
